CHANGES.txt
CONTRIBUTORS.txt
README.rst
README.txt
bootstrap.py
buildout.cfg
setup.py
buildout/__init__.py
buildout.eggscleaner.egg-info/PKG-INFO
buildout.eggscleaner.egg-info/SOURCES.txt
buildout.eggscleaner.egg-info/dependency_links.txt
buildout.eggscleaner.egg-info/entry_points.txt
buildout.eggscleaner.egg-info/namespace_packages.txt
buildout.eggscleaner.egg-info/not-zip-safe
buildout.eggscleaner.egg-info/requires.txt
buildout.eggscleaner.egg-info/top_level.txt
buildout/eggscleaner/__init__.py
buildout/eggscleaner/eggscleaner.txt
buildout/eggscleaner/tests.py