Metadata-Version: 1.0
Name: buildout.eggscleaner
Version: 0.1.5
Summary: A buildout extension to move non-used eggs to a specified directory
Home-page: https://github.com/thepjot/buildout.eggscleaner
Author: Peter Uittenbroek
Author-email: uittenbroek@goldmund-wyldebeast-wunderliebe.com
License: ZPL
Keywords: buildout extensions eggs directory clean
Platform: UNKNOWN
Classifier: Framework :: Buildout
Classifier: Intended Audience :: Developers
Classifier: Topic :: Software Development :: Build Tools
Classifier: License :: OSI Approved :: Zope Public License
